btq/__init__.py
btq/_version.py
btq/cli.py
btq/grpcProxy.py
btq/main.py
btq/measure.py
btq/core/AddressState.py
btq/core/Block.py
btq/core/BlockHeader.py
btq/core/BlockMetadata.py
btq/core/ChainManager.py
btq/core/DifficultyTracker.py
btq/core/ESyncState.py
btq/core/GenesisBlock.py
btq/core/Indexer.py
btq/core/LastTransactions.py
btq/core/Message.py
btq/core/MessageRequest.py
btq/core/Miner.py
btq/core/MultiSigAddressState.py
btq/core/OptimizedAddressState.py
btq/core/OutgoingMessage.py
btq/core/PaginatedBitfield.py
btq/core/PaginatedData.py
btq/core/PoWValidator.py
btq/core/ProposalRecord.py
btq/core/Singleton.py
btq/core/State.py
btq/core/StateContainer.py
btq/core/StateMigration.py
btq/core/TokenList.py
btq/core/TokenMetadata.py
btq/core/TransactionInfo.py
btq/core/TransactionMetadata.py
btq/core/TransactionPool.py
btq/core/VoteStats.py
btq/core/Wallet.py
btq/core/__init__.py
btq/core/btqnode.py
btq/core/config.py
btq/core/formulas.py
btq/core/genesis.yml
btq/core/messagereceipt.py
btq/core/node.py
btq/core/miners/__init__.py
btq/core/miners/qrandomx/QRXMiner.py
btq/core/miners/qrandomx/QRXPoWValidator.py
btq/core/miners/qrandomx/__init__.py
btq/core/miners/qryptonight7/CNv1Miner.py
btq/core/miners/qryptonight7/CNv1PoWValidator.py
btq/core/miners/qryptonight7/__init__.py
btq/core/misc/DependencyChecker.py
btq/core/misc/__init__.py
btq/core/misc/db.py
btq/core/misc/expiring_set.py
btq/core/misc/helper.py
btq/core/misc/logger.py
btq/core/misc/logger_twisted.py
btq/core/misc/ntp.py
btq/core/misc/set_logger.py
btq/core/notification/Observable.py
btq/core/notification/ObservableEvent.py
btq/core/notification/__init__.py
btq/core/p2p/IPMetadata.py
btq/core/p2p/__init__.py
btq/core/p2p/p2pChainManager.py
btq/core/p2p/p2pObservable.py
btq/core/p2p/p2pObserver.py
btq/core/p2p/p2pPeerManager.py
btq/core/p2p/p2pTxManagement.py
btq/core/p2p/p2pfactory.py
btq/core/p2p/p2pprotocol.py
btq/core/processors/TxnProcessor.py
btq/core/processors/__init__.py
btq/core/txs/CoinBase.py
bitcoinq-0.0.1.dist-info/LICENSE
bitcoinq-0.0.1.dist-info/METADATA
bitcoinq-0.0.1.dist-info/WHEEL
bitcoinq-0.0.1.dist-info/entry_points.txt
bitcoinq-0.0.1.dist-info/top_level.txt
bitcoinq-0.0.1.dist-info/RECORD
